snapshot_date
